README.md
setup.py
startpy/__init__.py
startpy.egg-info/PKG-INFO
startpy.egg-info/SOURCES.txt
startpy.egg-info/dependency_links.txt
startpy.egg-info/entry_points.txt
startpy.egg-info/requires.txt
startpy.egg-info/top_level.txt