Metadata-Version: 2.1
Name: startpy
Version: 0.0.1
Summary: cli tool for creating python project or library
Home-page: https://github.com/pypack/startpy
Author: PyPack
Author-email: g.cardamone2@gmail.com
License: UNKNOWN
Keywords: pypack python boilerplate package library
Platform: UNKNOWN
Classifier: Development Status :: 3 - Alpha
Classifier: Intended Audience :: Developers
Classifier: Topic :: Software Development :: Build Tools
Classifier: License :: OSI Approved :: MIT License
Classifier: Programming Language :: Python :: 2
Classifier: Programming Language :: Python :: 2.7
Classifier: Programming Language :: Python :: 3
Classifier: Programming Language :: Python :: 3.4
Classifier: Programming Language :: Python :: 3.5
Classifier: Programming Language :: Python :: 3.6
Classifier: Programming Language :: Python :: 3.7
Requires-Python: >=3.5
Provides-Extra: dev
Provides-Extra: test
